lexpp/__init__.py
lexpp/dict_builder.py
lexpp/dictionary.py
lexpp/entry.py
lexpp/lexpp.py
lexpp/res/synonyms.dict
lexpp-1.1.0.dist-info/DESCRIPTION.rst
lexpp-1.1.0.dist-info/METADATA
lexpp-1.1.0.dist-info/RECORD
lexpp-1.1.0.dist-info/WHEEL
lexpp-1.1.0.dist-info/metadata.json
lexpp-1.1.0.dist-info/top_level.txt
