Metadata-Version: 2.0
Name: lexpp
Version: 1.1.0
Summary: A lexical pre-processing module for Japanese text
Home-page: https://github.com/earlsuke
Author: earlsuke
Author-email: ryosuke.mitani@gmail.com
License: Apache-2.0
Platform: UNKNOWN
